{   
    "M" : {
        "Course" : "American and British Culture", 
        "SCHEMA" : 3,  
        "S3_BUCKET_NAME" : "abc-lms",    
        "DESIGN" : {
            "titleColor":"CRIMSON", 
            "bodyColor":"DEEPSKYBLUE", 
            "headTitle":"ABC course", 
            "headLogo": "https://abc-lms.s3-ap-northeast-1.amazonaws.com/profiles/US-UK-blend.png"
            }
    },

    "C" : [
        "120514112",
        "120554015",
        "120554054",
        "120554062",
        "120554125",
        "120654029",
        "120654033",
        "120654052",
        "120654065",
        "120812302",
        "120812316"
    ]

}

    

